{
	"info": {
		"_postman_id": "45060664-ff4bf9cd-4a38-4992-b94d-19d3a5108872",
		"name": "spring-security-practicals",
		"schema": "https://schema.getpostman.com/json/collection/v2.1.0/collection.json"
	},
	"item": [
		{
			"name": "usap",
			"item": [
				{
					"name": "Authentication",
					"item": [
						{
							"name": "New Request",
							"id": "45060664-f23a4af0-c9f8-405c-9059-9fc3e42a1b0c",
							"protocolProfileBehavior": {
								"disableBodyPruning": true
							},
							"request": {
								"method": "POST",
								"header": [],
								"url": {
									"raw": "localhost:8080/",
									"host": [
										"localhost"
									],
									"port": "8080",
									"path": [
										""
									]
								}
							},
							"response": []
						}
					],
					"id": "45060664-e0d988ca-1c7e-4120-84d5-b8ac0eebbdf6",
					"description": "<img src=\"https://content.pstmn.io/1fcf27fc-b51a-44e0-a015-37d2d710b388/aW1hZ2UucG5n\" alt=\"\n<br>\" height=\"811\" width=\"1212\">"
				},
				{
					"name": "Authorization",
					"item": [],
					"id": "45060664-7a709070-a168-435a-b1f3-430c44fa77d8"
				}
			],
			"id": "45060664-6de93a81-12f3-4217-9ff5-7b4d7e026947"
		},
		{
			"name": "New Request",
			"id": "45060664-cb098061-12d7-4605-a370-3c2fc961b47b",
			"protocolProfileBehavior": {
				"disableBodyPruning": true
			},
			"request": {
				"method": "GET",
				"header": [],
				"url": {
					"raw": "localhost:8080/",
					"host": [
						"localhost"
					],
					"port": "8080",
					"path": [
						""
					]
				}
			},
			"response": []
		},
		{
			"name": "New Request",
			"id": "45060664-21c87f38-d16e-4a22-a458-0683721b971a",
			"protocolProfileBehavior": {
				"disableBodyPruning": true
			},
			"request": {
				"method": "GET",
				"header": []
			},
			"response": []
		}
	]
}